jeeves/__init__.py
jeeves/cli/__init__.py
jeeves/cli/__main__.py
jeeves/cli/cli.py
jeeves/cli/echo.py
jeeves/conftest.py
jeeves/core/__init__.py
jeeves/core/actions/__init__.py
jeeves/core/actions/base.py
jeeves/core/actions/docker.py
jeeves/core/actions/files.py
jeeves/core/actions/shell.py
jeeves/core/actions/stub.py
jeeves/core/actions/tests/__init__.py
jeeves/core/actions/tests/test_base.py
jeeves/core/executor.py
jeeves/core/objects.py
jeeves/core/parsers.py
jeeves/core/registry.py
jeeves/core/tests/__init__.py
jeeves/core/tests/conftest.py
jeeves/core/tests/factories.py
jeeves/core/tests/tasks/__init__.py
jeeves/core/tests/tasks/test_shell.py
jeeves/core/tests/test_executor.py
jeeves/core/tests/test_parsers.py
jeeves/core/tests/test_registry.py
jeeves/frontend/forms.py
jeeves/frontend/templates/_base.j2
jeeves/frontend/templates/dashboard.j2
jeeves/frontend/templates/flows/_base.j2
jeeves/frontend/templates/flows/_detail.j2
jeeves/frontend/templates/flows/add.j2
jeeves/frontend/templates/flows/delete.j2
jeeves/frontend/templates/flows/execution-delete.j2
jeeves/frontend/templates/flows/execution-detail.j2
jeeves/frontend/templates/flows/execution-list.j2
jeeves/frontend/templates/flows/list.j2
jeeves/frontend/templates/flows/task-add.j2
jeeves/frontend/templates/flows/task-list.j2
jeeves/frontend/templatetags/__init__.py
jeeves/frontend/templatetags/batch.py
jeeves/frontend/templatetags/bulma.py
jeeves/frontend/urls.py
jeeves/frontend/views.py
jeeves-0.1.0a3.dist-info/entry_points.txt
jeeves-0.1.0a3.dist-info/WHEEL
jeeves-0.1.0a3.dist-info/METADATA
jeeves-0.1.0a3.dist-info/RECORD
