Metadata-Version: 2.1
Name: jeeves
Version: 0.1.0a3
Summary: 
Author: Felipe Martin
Author-email: me@fmartingr.com
Requires-Python: >=3.7,<4.0
Classifier: Programming Language :: Python :: 3
Classifier: Programming Language :: Python :: 3.7
Classifier: Programming Language :: Python :: 3.8
Requires-Dist: click (>=7.0,<8.0)
Requires-Dist: docker (>=4.1.0,<5.0.0)
Requires-Dist: jinja2 (>=2.10,<3.0)
Requires-Dist: pydantic (>=0.32.2,<0.33.0)
Requires-Dist: pyyaml (>=5.3.1,<6.0.0)
Requires-Dist: toml (>=0.10.0,<0.11.0)
